openimis_be_payroll-1.4.0.dist-info/licenses/LICENSE.md
payroll/__init__.py
payroll/admin.py
payroll/apps.py
payroll/documents.py
payroll/gql_mutations.py
payroll/gql_queries.py
payroll/models.py
payroll/schema.py
payroll/services.py
payroll/signals.py
payroll/tasks.py
payroll/urls.py
payroll/utils.py
payroll/validation.py
payroll/views.py
payroll/migrations/0001_initial.py
payroll/migrations/0002_add_pp_rights_to_admin.py
payroll/migrations/0003_historicalpayroll_historicalpayrollbill_payroll_payrollbill.py
payroll/migrations/0004_add_payroll_rights_to_admin.py
payroll/migrations/0005_change_i_user_to_user.py
payroll/migrations/0006_auto_20230809_1057.py
payroll/migrations/0007_auto_20230811_0734.py
payroll/migrations/0008_historicalpaymentadaptorhistory_paymentadaptorhistory.py
payroll/migrations/0009_auto_20231006_0755.py
payroll/migrations/0010_alter_paymentpoint_ppm.py
payroll/migrations/0010_auto_20240131_1015.py
payroll/migrations/0011_auto_20240202_1140.py
payroll/migrations/0012_auto_20240202_1619.py
payroll/migrations/0013_merge_20240207_1633.py
payroll/migrations/0013_payrollmutation.py
payroll/migrations/0014_alter_benefitattachment_date_created_and_more.py
payroll/migrations/0015_merge_20240207_1703.py
payroll/migrations/0016_add_csv_rec_upload_rigth.py
payroll/migrations/0017_csvreconciliationupload_historicalcsvreconciliationupload.py
payroll/migrations/0018_auto_20240212_1355.py
payroll/migrations/0019_auto_20240221_2330.py
payroll/migrations/0020_auto_20240227_0912.py
payroll/migrations/0021_auto_20240715_0855.py
payroll/migrations/0022_alter_csvreconciliationupload_user_created_and_more.py
payroll/migrations/__init__.py
payroll/payment_gateway/__init__.py
payroll/payment_gateway/mocked_payment_gateway_connector.py
payroll/payment_gateway/payment_gateway_config.py
payroll/payment_gateway/payment_gateway_connector.py
payroll/payments_registry/__init__.py
payroll/payments_registry/registry_point.py
payroll/payments_registry/storage.py
payroll/strategies/__init__.py
openimis_be_payroll-1.4.0.dist-info/METADATA
openimis_be_payroll-1.4.0.dist-info/WHEEL
openimis_be_payroll-1.4.0.dist-info/top_level.txt
openimis_be_payroll-1.4.0.dist-info/RECORD
